README.md
setup.py
pcrawler.egg-info/PKG-INFO
pcrawler.egg-info/SOURCES.txt
pcrawler.egg-info/dependency_links.txt
pcrawler.egg-info/entry_points.txt
pcrawler.egg-info/top_level.txt
src/__init__.py
src/main.py
src/config/Config.py
src/config/Install.py
src/config/__init__.py
src/core/Crawler.py
src/core/Page.py
src/core/__init__.py
src/downloader/SimpleDownloader.py
src/downloader/__init__.py
src/monitor/CrawlerMonitor.py
src/monitor/MonitorModel.py
src/monitor/__init__.py
src/processor/PageProcess.py
src/processor/__init__.py
src/processor/builtin/ImagePageProcess.py
src/processor/builtin/SinaNewsPageProcessor.py
src/processor/builtin/VedioPageProcess.py
src/processor/builtin/__init__.py
src/processor/loophole/NsfocusLoopholePageProcess.py
src/processor/loophole/__init__.py
src/scheduler/FileCacheScheduler.py
src/scheduler/HashSetScheduler.py
src/scheduler/Schedular.py
src/scheduler/__init__.py
src/scheduler/duplicate/BloomFilterDuplicateRemover.py
src/scheduler/duplicate/DuplicateRemover.py
src/scheduler/duplicate/FileCacheDuplicate.py
src/scheduler/duplicate/HashSetDuplicateRemover.py
src/scheduler/duplicate/__init__.py
src/storage/ConsoleStorage.py
src/storage/Storage.py
src/storage/__init__.py
src/storage/basic/CsvStorage.py
src/storage/basic/JsonStorage.py
src/storage/basic/MediaStorage.py
src/storage/basic/__init__.py
src/storage/data/KafkaStorage.py
src/storage/data/__init__.py
src/storage/hadoop/AvroStorage.py
src/storage/hadoop/ParquetStorage.py
src/storage/hadoop/__init__.py
src/util/ElementUtil.py
src/util/__init__.py
src/util/coverageUtil.py
test/__init__.py
test/core/CrawlerTest.py
test/core/__init__.py
test/downloader/SimpleDownloaderTest.py
test/downloader/__init__.py
test/processor/NsfocusLoopholePageProcessTest.py
test/processor/VedioPageProcessTest.py
test/processor/__init__.py
test/storage/AvroStorageTest.py
test/storage/__init__.py
test/storage/basic/CsvStorageTest.py
test/storage/basic/MediaStorageTest.py
test/storage/basic/__init__.py