Metadata-Version: 2.1
Name: pcrawler
Version: 0.0.3
Summary: python版本的爬虫程序。根据java版本的webmagic改编而成。该爬虫程序主要包含downloader、storage、processor、schemular等四大功能模块。通过该爬虫程序可以快速的编写一个自定义的爬虫程序。
Home-page: https://github.com/mumupy/pcrawler.git
Author: 甘亮
Author-email: lovercws@gmail.com
License: Apache License
Keywords: python版本的爬虫程序
Platform: any
